ovos_ww_plugin_snowboy/__init__.py
ovos_ww_plugin_snowboy/exceptions.py
ovos_ww_plugin_snowboy/snowboydecoder.py
ovos_ww_plugin_snowboy/version.py
ovos_ww_plugin_snowboy/lib/linux/_snowboydetect.so
ovos_ww_plugin_snowboy/lib/linux/snowboydetect.py
ovos_ww_plugin_snowboy/lib/rpi/_snowboydetect.so
ovos_ww_plugin_snowboy/lib/rpi/snowboydetect.py
ovos_ww_plugin_snowboy/resources/common.res
ovos_ww_plugin_snowboy/resources/ding.wav
ovos_ww_plugin_snowboy/resources/dong.wav
ovos_ww_plugin_snowboy/resources/models/alexa.umdl
ovos_ww_plugin_snowboy/resources/models/computer.umdl
ovos_ww_plugin_snowboy/resources/models/hey_extreme.umdl
ovos_ww_plugin_snowboy/resources/models/jarvis.umdl
ovos_ww_plugin_snowboy/resources/models/neoya.umdl
ovos_ww_plugin_snowboy/resources/models/smart_mirror.umdl
ovos_ww_plugin_snowboy/resources/models/snowboy.umdl
ovos_ww_plugin_snowboy/resources/models/subex.umdl
ovos_ww_plugin_snowboy/resources/models/view_glass.umdl
ovos_ww_plugin_snowboy-0.1.3a1.dist-info/LICENSE
ovos_ww_plugin_snowboy-0.1.3a1.dist-info/METADATA
ovos_ww_plugin_snowboy-0.1.3a1.dist-info/WHEEL
ovos_ww_plugin_snowboy-0.1.3a1.dist-info/entry_points.txt
ovos_ww_plugin_snowboy-0.1.3a1.dist-info/top_level.txt
ovos_ww_plugin_snowboy-0.1.3a1.dist-info/zip-safe
ovos_ww_plugin_snowboy-0.1.3a1.dist-info/RECORD
